uwstyle/__init__.py
uwstyle/dialogs/__init__.py
uwstyle/dialogs/dialogs.py
uwstyle/dialogs/slctbox.py
uwstyle/excel/__init__.py
uwstyle/excel/sheet.py
uwstyle/excel/workbook.py
uwstyle/overridestd/writer.py
uwstyle/webbrowser/__init__.py
uwstyle/webbrowser/driver.py
uwstyle/webbrowser/element.py
uwstyle-0.0.6.dist-info/LICENSE
uwstyle-0.0.6.dist-info/METADATA
uwstyle-0.0.6.dist-info/WHEEL
uwstyle-0.0.6.dist-info/top_level.txt
uwstyle-0.0.6.dist-info/RECORD
