Metadata-Version: 2.1
Name: uwstyle
Version: 0.0.6
Summary: Modules for handling UWSC styles in Python
Home-page: https://github.com/TakamiChie/UWStyleMethods
Author: TakamiChie
Author-email: chie@onpu-tamago.net
License: MIT
Keywords: dialog utility
Platform: UNKNOWN
Classifier: Programming Language :: Python :: 3.7
Requires-Dist: selenium (>=3.141.0)
Requires-Dist: pywin32 (>=224)
